rabdam/__init__.py
rabdam/rabdam.py
rabdam/Subroutines/BDamage.py
rabdam/Subroutines/CalculateBDamage.py
rabdam/Subroutines/HTML_stylesheet.css
rabdam/Subroutines/HTML_stylesheet.js
rabdam/Subroutines/PDBCUR.py
rabdam/Subroutines/__init__.py
rabdam/Subroutines/bdb_list.py
rabdam/Subroutines/checkDependencies.py
rabdam/Subroutines/makeDataFrame.py
rabdam/Subroutines/output.py
rabdam/Subroutines/parsePDB.py
rabdam/Subroutines/translateUnitCell.py
rabdam/Subroutines/trimUnitCellAssembly.py
rabdam-1.4.1.dist-info/METADATA
rabdam-1.4.1.dist-info/RECORD
rabdam-1.4.1.dist-info/WHEEL
rabdam-1.4.1.dist-info/entry_points.txt
rabdam-1.4.1.dist-info/top_level.txt
