Metadata-Version: 2.1
Name: rabdam
Version: 1.4.1
Summary: RABDAM: A program to identify and quantify specific radiation damage within individual protein crystal structures
Home-page: https://github.com/GarmanGroup/RABDAM
Author: Kathryn Shelley, Thomas Dixon and Jonathan Brooks-Bartlett in the lab of Professor Elspeth Garman, University of Oxford
Author-email: kathryn.l.shelley@gmail.com
License: LGPL v3
Keywords: radiation damage,specific damage,atomic Bfactors,atomic displacement parameters,BDamage,Bnet
Platform: UNKNOWN
Classifier: Programming Language :: Python
Requires-Python: >=2.7, !=3.0.*, !=3.1.*, !=3.2.*, !=3.3.*, !=3.4.*, !=3.5.*, <4
Requires-Dist: numpy
Requires-Dist: matplotlib
Requires-Dist: seaborn
Requires-Dist: pandas
Requires-Dist: requests
Requires-Dist: setuptools
